[
  {
    "name": "<operator>.fieldAccess",
    "signature": "",
    "code": "this.Addresses",
    "typeFullName": "java.util.ArrayList<BuddyInfo>",
    "columnNumber": 9,
    "order": 1,
    "methodFullName": "<operator>.fieldAccess",
    "_label": "CALL",
    "argumentIndex": 1,
    "dynamicTypeHintFullName": [],
    "dispatchType": "STATIC_DISPATCH",
    "lineNumber": 9,
    "id": 24
  },
  {
    "dynamicTypeHintFullName": [],
    "code": "<empty>",
    "typeFullName": "java.util.ArrayList",
    "columnNumber": 21,
    "order": 2,
    "_label": "BLOCK",
    "argumentIndex": 2,
    "lineNumber": 9,
    "id": 27
  },
  {
    "dynamicTypeHintFullName": [],
    "name": "this",
    "code": "this",
    "typeFullName": "main.python.joernTestProject.src.AddressBook",
    "columnNumber": 9,
    "order": 1,
    "_label": "IDENTIFIER",
    "argumentIndex": 1,
    "lineNumber": 9,
    "id": 25
  },
  {
    "code": "Addresses",
    "columnNumber": 9,
    "order": 2,
    "_label": "FIELD_IDENTIFIER",
    "argumentIndex": 2,
    "canonicalName": "Addresses",
    "lineNumber": 9,
    "id": 26
  },
  {
    "dynamicTypeHintFullName": [],
    "name": "$obj0",
    "code": "$obj0",
    "typeFullName": "java.util.ArrayList",
    "order": 1,
    "_label": "IDENTIFIER",
    "argumentIndex": 1,
    "id": 29
  },
  {
    "name": "<operator>.alloc",
    "signature": "java.util.ArrayList()",
    "code": "new ArrayList<>()",
    "typeFullName": "java.util.ArrayList",
    "columnNumber": 21,
    "order": 2,
    "methodFullName": "<operator>.alloc",
    "_label": "CALL",
    "argumentIndex": 2,
    "dynamicTypeHintFullName": [],
    "dispatchType": "STATIC_DISPATCH",
    "lineNumber": 9,
    "id": 30
  },
  {
    "dynamicTypeHintFullName": [],
    "name": "$obj0",
    "code": "$obj0",
    "typeFullName": "java.util.ArrayList",
    "order": 1,
    "_label": "IDENTIFIER",
    "argumentIndex": 0,
    "id": 32
  },
  {
    "dynamicTypeHintFullName": [],
    "name": "newBuddy",
    "code": "newBuddy",
    "typeFullName": "java.util.BuddyInfo",
    "columnNumber": 12,
    "order": 1,
    "_label": "IDENTIFIER",
    "argumentIndex": 1,
    "lineNumber": 14,
    "id": 41
  },
  {
    "dynamicTypeHintFullName": [],
    "code": "null",
    "typeFullName": "null",
    "columnNumber": 24,
    "order": 2,
    "_label": "LITERAL",
    "argumentIndex": 2,
    "lineNumber": 14,
    "id": 42
  },
  {
    "name": "<operator>.fieldAccess",
    "signature": "",
    "code": "this.Addresses",
    "typeFullName": "java.util.ArrayList<BuddyInfo>",
    "columnNumber": 12,
    "order": 1,
    "methodFullName": "<operator>.fieldAccess",
    "_label": "CALL",
    "argumentIndex": 0,
    "dynamicTypeHintFullName": [],
    "dispatchType": "STATIC_DISPATCH",
    "lineNumber": 16,
    "id": 45
  },
  {
    "dynamicTypeHintFullName": [],
    "name": "newBuddy",
    "code": "newBuddy",
    "typeFullName": "java.util.BuddyInfo",
    "columnNumber": 26,
    "order": 2,
    "_label": "IDENTIFIER",
    "argumentIndex": 1,
    "lineNumber": 16,
    "id": 48
  },
  {
    "dynamicTypeHintFullName": [],
    "name": "this",
    "code": "this",
    "typeFullName": "main.python.joernTestProject.src.AddressBook",
    "columnNumber": 12,
    "order": 1,
    "_label": "IDENTIFIER",
    "argumentIndex": 1,
    "lineNumber": 16,
    "id": 46
  },
  {
    "code": "Addresses",
    "columnNumber": 12,
    "order": 2,
    "_label": "FIELD_IDENTIFIER",
    "argumentIndex": 2,
    "canonicalName": "Addresses",
    "lineNumber": 16,
    "id": 47
  },
  {
    "name": "<operator>.greaterEqualsThan",
    "signature": "",
    "code": "index >= 0",
    "typeFullName": "boolean",
    "columnNumber": 12,
    "order": 1,
    "methodFullName": "<operator>.greaterEqualsThan",
    "_label": "CALL",
    "argumentIndex": 1,
    "dynamicTypeHintFullName": [],
    "dispatchType": "STATIC_DISPATCH",
    "lineNumber": 22,
    "id": 58
  },
  {
    "name": "<operator>.lessThan",
    "signature": "",
    "code": "index < Addresses.size()",
    "typeFullName": "boolean",
    "columnNumber": 26,
    "order": 2,
    "methodFullName": "<operator>.lessThan",
    "_label": "CALL",
    "argumentIndex": 2,
    "dynamicTypeHintFullName": [],
    "dispatchType": "STATIC_DISPATCH",
    "lineNumber": 22,
    "id": 61
  },
  {
    "dynamicTypeHintFullName": [],
    "name": "index",
    "code": "index",
    "typeFullName": "int",
    "columnNumber": 12,
    "order": 1,
    "_label": "IDENTIFIER",
    "argumentIndex": 1,
    "lineNumber": 22,
    "id": 59
  },
  {
    "dynamicTypeHintFullName": [],
    "code": "0",
    "typeFullName": "int",
    "columnNumber": 21,
    "order": 2,
    "_label": "LITERAL",
    "argumentIndex": 2,
    "lineNumber": 22,
    "id": 60
  },
  {
    "dynamicTypeHintFullName": [],
    "name": "index",
    "code": "index",
    "typeFullName": "int",
    "columnNumber": 26,
    "order": 1,
    "_label": "IDENTIFIER",
    "argumentIndex": 1,
    "lineNumber": 22,
    "id": 62
  },
  {
    "name": "size",
    "signature": "<unresolvedSignature>(0)",
    "code": "size()",
    "typeFullName": "boolean",
    "columnNumber": 34,
    "order": 2,
    "methodFullName": "java.util.ArrayList<BuddyInfo>.size:<unresolvedSignature>(0)",
    "_label": "CALL",
    "argumentIndex": 2,
    "dynamicTypeHintFullName": [],
    "dispatchType": "DYNAMIC_DISPATCH",
    "lineNumber": 22,
    "id": 63
  },
  {
    "name": "<operator>.fieldAccess",
    "signature": "",
    "code": "this.Addresses",
    "typeFullName": "java.util.ArrayList<BuddyInfo>",
    "columnNumber": 34,
    "order": 1,
    "methodFullName": "<operator>.fieldAccess",
    "_label": "CALL",
    "argumentIndex": 0,
    "dynamicTypeHintFullName": [],
    "dispatchType": "STATIC_DISPATCH",
    "lineNumber": 22,
    "id": 64
  },
  {
    "dynamicTypeHintFullName": [],
    "name": "this",
    "code": "this",
    "typeFullName": "main.python.joernTestProject.src.AddressBook",
    "columnNumber": 34,
    "order": 1,
    "_label": "IDENTIFIER",
    "argumentIndex": 1,
    "lineNumber": 22,
    "id": 65
  },
  {
    "code": "Addresses",
    "columnNumber": 34,
    "order": 2,
    "_label": "FIELD_IDENTIFIER",
    "argumentIndex": 2,
    "canonicalName": "Addresses",
    "lineNumber": 22,
    "id": 66
  },
  {
    "name": "<operator>.fieldAccess",
    "signature": "",
    "code": "this.Addresses",
    "typeFullName": "java.util.ArrayList<BuddyInfo>",
    "columnNumber": 13,
    "order": 1,
    "methodFullName": "<operator>.fieldAccess",
    "_label": "CALL",
    "argumentIndex": 0,
    "dynamicTypeHintFullName": [],
    "dispatchType": "STATIC_DISPATCH",
    "lineNumber": 24,
    "id": 69
  },
  {
    "dynamicTypeHintFullName": [],
    "name": "index",
    "code": "index",
    "typeFullName": "int",
    "columnNumber": 30,
    "order": 2,
    "_label": "IDENTIFIER",
    "argumentIndex": 1,
    "lineNumber": 24,
    "id": 72
  },
  {
    "dynamicTypeHintFullName": [],
    "name": "this",
    "code": "this",
    "typeFullName": "main.python.joernTestProject.src.AddressBook",
    "columnNumber": 13,
    "order": 1,
    "_label": "IDENTIFIER",
    "argumentIndex": 1,
    "lineNumber": 24,
    "id": 70
  },
  {
    "code": "Addresses",
    "columnNumber": 13,
    "order": 2,
    "_label": "FIELD_IDENTIFIER",
    "argumentIndex": 2,
    "canonicalName": "Addresses",
    "lineNumber": 24,
    "id": 71
  },
  {
    "dynamicTypeHintFullName": [],
    "name": "bud",
    "code": "bud",
    "typeFullName": "ANY",
    "columnNumber": 19,
    "order": 1,
    "_label": "IDENTIFIER",
    "argumentIndex": 1,
    "lineNumber": 31,
    "id": 83
  },
  {
    "name": "<operator>.alloc",
    "signature": "ANY()",
    "code": "new BuddyInfo(\"Bob\", \"Carleton\", \"613\")",
    "typeFullName": "ANY",
    "columnNumber": 25,
    "order": 2,
    "methodFullName": "<operator>.alloc",
    "_label": "CALL",
    "argumentIndex": 2,
    "dynamicTypeHintFullName": [],
    "dispatchType": "STATIC_DISPATCH",
    "lineNumber": 31,
    "id": 84
  },
  {
    "dynamicTypeHintFullName": [],
    "name": "bud",
    "code": "bud",
    "typeFullName": "ANY",
    "columnNumber": 19,
    "order": 1,
    "_label": "IDENTIFIER",
    "argumentIndex": 0,
    "lineNumber": 31,
    "id": 86
  },
  {
    "dynamicTypeHintFullName": [],
    "code": "\"Bob\"",
    "typeFullName": "java.lang.String",
    "columnNumber": 40,
    "order": 2,
    "_label": "LITERAL",
    "argumentIndex": 1,
    "lineNumber": 31,
    "id": 87
  },
  {
    "dynamicTypeHintFullName": [],
    "code": "\"Carleton\"",
    "typeFullName": "java.lang.String",
    "columnNumber": 47,
    "order": 3,
    "_label": "LITERAL",
    "argumentIndex": 2,
    "lineNumber": 31,
    "id": 88
  },
  {
    "dynamicTypeHintFullName": [],
    "code": "\"613\"",
    "typeFullName": "java.lang.String",
    "columnNumber": 59,
    "order": 4,
    "_label": "LITERAL",
    "argumentIndex": 3,
    "lineNumber": 31,
    "id": 89
  },
  {
    "dynamicTypeHintFullName": [],
    "name": "addBook",
    "code": "addBook",
    "typeFullName": "main.python.joernTestProject.src.AddressBook",
    "columnNumber": 21,
    "order": 1,
    "_label": "IDENTIFIER",
    "argumentIndex": 1,
    "lineNumber": 32,
    "id": 92
  },
  {
    "name": "<operator>.alloc",
    "signature": "main.python.joernTestProject.src.AddressBook()",
    "code": "new AddressBook()",
    "typeFullName": "main.python.joernTestProject.src.AddressBook",
    "columnNumber": 31,
    "order": 2,
    "methodFullName": "<operator>.alloc",
    "_label": "CALL",
    "argumentIndex": 2,
    "dynamicTypeHintFullName": [],
    "dispatchType": "STATIC_DISPATCH",
    "lineNumber": 32,
    "id": 93
  },
  {
    "dynamicTypeHintFullName": [],
    "name": "addBook",
    "code": "addBook",
    "typeFullName": "main.python.joernTestProject.src.AddressBook",
    "columnNumber": 21,
    "order": 1,
    "_label": "IDENTIFIER",
    "argumentIndex": 0,
    "lineNumber": 32,
    "id": 95
  },
  {
    "dynamicTypeHintFullName": [],
    "name": "addBook",
    "code": "addBook",
    "typeFullName": "main.python.joernTestProject.src.AddressBook",
    "columnNumber": 9,
    "order": 1,
    "_label": "IDENTIFIER",
    "argumentIndex": 0,
    "lineNumber": 33,
    "id": 97
  },
  {
    "dynamicTypeHintFullName": [],
    "name": "bud",
    "code": "bud",
    "typeFullName": "ANY",
    "columnNumber": 26,
    "order": 2,
    "_label": "IDENTIFIER",
    "argumentIndex": 1,
    "lineNumber": 33,
    "id": 98
  },
  {
    "dynamicTypeHintFullName": [],
    "name": "addBook",
    "code": "addBook",
    "typeFullName": "main.python.joernTestProject.src.AddressBook",
    "columnNumber": 9,
    "order": 1,
    "_label": "IDENTIFIER",
    "argumentIndex": 0,
    "lineNumber": 34,
    "id": 100
  },
  {
    "dynamicTypeHintFullName": [],
    "code": "0",
    "typeFullName": "int",
    "columnNumber": 29,
    "order": 2,
    "_label": "LITERAL",
    "argumentIndex": 1,
    "lineNumber": 34,
    "id": 101
  },
  {
    "name": "<operator>.fieldAccess",
    "signature": "",
    "code": "System.out",
    "typeFullName": "java.io.PrintStream",
    "columnNumber": 9,
    "order": 1,
    "methodFullName": "<operator>.fieldAccess",
    "_label": "CALL",
    "argumentIndex": 0,
    "dynamicTypeHintFullName": [],
    "dispatchType": "STATIC_DISPATCH",
    "lineNumber": 35,
    "id": 103
  },
  {
    "name": "getName",
    "signature": "<unresolvedSignature>(0)",
    "code": "getName()",
    "typeFullName": "ANY",
    "columnNumber": 29,
    "order": 2,
    "methodFullName": "ANY.getName:<unresolvedSignature>(0)",
    "_label": "CALL",
    "argumentIndex": 1,
    "dynamicTypeHintFullName": [],
    "dispatchType": "DYNAMIC_DISPATCH",
    "lineNumber": 35,
    "id": 106
  },
  {
    "dynamicTypeHintFullName": [],
    "name": "System",
    "code": "System",
    "typeFullName": "java.lang.System",
    "columnNumber": 9,
    "order": 1,
    "_label": "IDENTIFIER",
    "argumentIndex": 1,
    "lineNumber": 35,
    "id": 104
  },
  {
    "code": "out",
    "columnNumber": 16,
    "order": 2,
    "_label": "FIELD_IDENTIFIER",
    "argumentIndex": 2,
    "canonicalName": "out",
    "lineNumber": 35,
    "id": 105
  },
  {
    "dynamicTypeHintFullName": [],
    "name": "bud",
    "code": "bud",
    "typeFullName": "ANY",
    "columnNumber": 29,
    "order": 1,
    "_label": "IDENTIFIER",
    "argumentIndex": 0,
    "lineNumber": 35,
    "id": 107
  },
  {
    "name": "<operator>.fieldAccess",
    "signature": "",
    "code": "this.name",
    "typeFullName": "java.lang.String",
    "columnNumber": 9,
    "order": 1,
    "methodFullName": "<operator>.fieldAccess",
    "_label": "CALL",
    "argumentIndex": 1,
    "dynamicTypeHintFullName": [],
    "dispatchType": "STATIC_DISPATCH",
    "lineNumber": 9,
    "id": 142
  },
  {
    "dynamicTypeHintFullName": [],
    "name": "name",
    "code": "name",
    "typeFullName": "java.lang.String",
    "columnNumber": 21,
    "order": 2,
    "_label": "IDENTIFIER",
    "argumentIndex": 2,
    "lineNumber": 9,
    "id": 144
  },
  {
    "dynamicTypeHintFullName": [],
    "name": "this",
    "code": "this",
    "typeFullName": "main.python.joernTestProject.src.BuddyInfo",
    "columnNumber": 9,
    "order": 1,
    "_label": "IDENTIFIER",
    "argumentIndex": 1,
    "lineNumber": 9,
    "id": 112
  },
  {
    "code": "name",
    "columnNumber": 14,
    "order": 2,
    "_label": "FIELD_IDENTIFIER",
    "argumentIndex": 2,
    "canonicalName": "name",
    "lineNumber": 9,
    "id": 143
  },
  {
    "name": "<operator>.fieldAccess",
    "signature": "",
    "code": "this.address",
    "typeFullName": "java.lang.String",
    "columnNumber": 9,
    "order": 1,
    "methodFullName": "<operator>.fieldAccess",
    "_label": "CALL",
    "argumentIndex": 1,
    "dynamicTypeHintFullName": [],
    "dispatchType": "STATIC_DISPATCH",
    "lineNumber": 10,
    "id": 146
  },
  {
    "dynamicTypeHintFullName": [],
    "name": "address",
    "code": "address",
    "typeFullName": "java.lang.String",
    "columnNumber": 24,
    "order": 2,
    "_label": "IDENTIFIER",
    "argumentIndex": 2,
    "lineNumber": 10,
    "id": 148
  },
  {
    "dynamicTypeHintFullName": [],
    "name": "this",
    "code": "this",
    "typeFullName": "main.python.joernTestProject.src.BuddyInfo",
    "columnNumber": 9,
    "order": 1,
    "_label": "IDENTIFIER",
    "argumentIndex": 1,
    "lineNumber": 10,
    "id": 114
  },
  {
    "code": "address",
    "columnNumber": 14,
    "order": 2,
    "_label": "FIELD_IDENTIFIER",
    "argumentIndex": 2,
    "canonicalName": "address",
    "lineNumber": 10,
    "id": 147
  },
  {
    "name": "<operator>.fieldAccess",
    "signature": "",
    "code": "this.phone_num",
    "typeFullName": "java.lang.String",
    "columnNumber": 9,
    "order": 1,
    "methodFullName": "<operator>.fieldAccess",
    "_label": "CALL",
    "argumentIndex": 1,
    "dynamicTypeHintFullName": [],
    "dispatchType": "STATIC_DISPATCH",
    "lineNumber": 11,
    "id": 150
  },
  {
    "dynamicTypeHintFullName": [],
    "name": "phone_num",
    "code": "phone_num",
    "typeFullName": "java.lang.String",
    "columnNumber": 26,
    "order": 2,
    "_label": "IDENTIFIER",
    "argumentIndex": 2,
    "lineNumber": 11,
    "id": 152
  },
  {
    "dynamicTypeHintFullName": [],
    "name": "this",
    "code": "this",
    "typeFullName": "main.python.joernTestProject.src.BuddyInfo",
    "columnNumber": 9,
    "order": 1,
    "_label": "IDENTIFIER",
    "argumentIndex": 1,
    "lineNumber": 11,
    "id": 115
  },
  {
    "code": "phone_num",
    "columnNumber": 14,
    "order": 2,
    "_label": "FIELD_IDENTIFIER",
    "argumentIndex": 2,
    "canonicalName": "phone_num",
    "lineNumber": 11,
    "id": 151
  },
  {
    "dynamicTypeHintFullName": [],
    "name": "this",
    "code": "this",
    "typeFullName": "main.python.joernTestProject.src.BuddyInfo",
    "columnNumber": 16,
    "order": 1,
    "_label": "IDENTIFIER",
    "argumentIndex": 1,
    "lineNumber": 16,
    "id": 159
  },
  {
    "code": "name",
    "columnNumber": 16,
    "order": 2,
    "_label": "FIELD_IDENTIFIER",
    "argumentIndex": 2,
    "canonicalName": "name",
    "lineNumber": 16,
    "id": 160
  },
  {
    "dynamicTypeHintFullName": [],
    "name": "friend1",
    "code": "friend1",
    "typeFullName": "main.python.joernTestProject.src.BuddyInfo",
    "columnNumber": 19,
    "order": 1,
    "_label": "IDENTIFIER",
    "argumentIndex": 1,
    "lineNumber": 21,
    "id": 169
  },
  {
    "name": "<operator>.alloc",
    "signature": "main.python.joernTestProject.src.BuddyInfo()",
    "code": "new BuddyInfo(\"Homer\", \"Carleton\", \"613\")",
    "typeFullName": "main.python.joernTestProject.src.BuddyInfo",
    "columnNumber": 29,
    "order": 2,
    "methodFullName": "<operator>.alloc",
    "_label": "CALL",
    "argumentIndex": 2,
    "dynamicTypeHintFullName": [],
    "dispatchType": "STATIC_DISPATCH",
    "lineNumber": 21,
    "id": 170
  },
  {
    "dynamicTypeHintFullName": [],
    "name": "friend1",
    "code": "friend1",
    "typeFullName": "main.python.joernTestProject.src.BuddyInfo",
    "columnNumber": 19,
    "order": 1,
    "_label": "IDENTIFIER",
    "argumentIndex": 0,
    "lineNumber": 21,
    "id": 172
  },
  {
    "dynamicTypeHintFullName": [],
    "code": "\"Homer\"",
    "typeFullName": "java.lang.String",
    "columnNumber": 43,
    "order": 2,
    "_label": "LITERAL",
    "argumentIndex": 1,
    "lineNumber": 21,
    "id": 173
  },
  {
    "dynamicTypeHintFullName": [],
    "code": "\"Carleton\"",
    "typeFullName": "java.lang.String",
    "columnNumber": 52,
    "order": 3,
    "_label": "LITERAL",
    "argumentIndex": 2,
    "lineNumber": 21,
    "id": 174
  },
  {
    "dynamicTypeHintFullName": [],
    "code": "\"613\"",
    "typeFullName": "java.lang.String",
    "columnNumber": 64,
    "order": 4,
    "_label": "LITERAL",
    "argumentIndex": 3,
    "lineNumber": 21,
    "id": 175
  },
  {
    "name": "<operator>.fieldAccess",
    "signature": "",
    "code": "System.out",
    "typeFullName": "java.io.PrintStream",
    "columnNumber": 9,
    "order": 1,
    "methodFullName": "<operator>.fieldAccess",
    "_label": "CALL",
    "argumentIndex": 0,
    "dynamicTypeHintFullName": [],
    "dispatchType": "STATIC_DISPATCH",
    "lineNumber": 22,
    "id": 177
  },
  {
    "name": "<operator>.addition",
    "signature": "",
    "code": "\"Hello \" + friend1.getName()",
    "typeFullName": "java.lang.String",
    "columnNumber": 29,
    "order": 2,
    "methodFullName": "<operator>.addition",
    "_label": "CALL",
    "argumentIndex": 1,
    "dynamicTypeHintFullName": [],
    "dispatchType": "STATIC_DISPATCH",
    "lineNumber": 22,
    "id": 180
  },
  {
    "dynamicTypeHintFullName": [],
    "name": "System",
    "code": "System",
    "typeFullName": "java.lang.System",
    "columnNumber": 9,
    "order": 1,
    "_label": "IDENTIFIER",
    "argumentIndex": 1,
    "lineNumber": 22,
    "id": 178
  },
  {
    "code": "out",
    "columnNumber": 16,
    "order": 2,
    "_label": "FIELD_IDENTIFIER",
    "argumentIndex": 2,
    "canonicalName": "out",
    "lineNumber": 22,
    "id": 179
  },
  {
    "dynamicTypeHintFullName": [],
    "code": "\"Hello \"",
    "typeFullName": "java.lang.String",
    "columnNumber": 29,
    "order": 1,
    "_label": "LITERAL",
    "argumentIndex": 1,
    "lineNumber": 22,
    "id": 181
  },
  {
    "name": "getName",
    "signature": "java.lang.String()",
    "code": "friend1.getName()",
    "typeFullName": "java.lang.String",
    "columnNumber": 40,
    "order": 2,
    "methodFullName": "main.python.joernTestProject.src.BuddyInfo.getName:java.lang.String()",
    "_label": "CALL",
    "argumentIndex": 2,
    "dynamicTypeHintFullName": [],
    "dispatchType": "DYNAMIC_DISPATCH",
    "lineNumber": 22,
    "id": 182
  },
  {
    "dynamicTypeHintFullName": [],
    "name": "friend1",
    "code": "friend1",
    "typeFullName": "main.python.joernTestProject.src.BuddyInfo",
    "columnNumber": 40,
    "order": 1,
    "_label": "IDENTIFIER",
    "argumentIndex": 0,
    "lineNumber": 22,
    "id": 183
  }
]
